ref/__init__.py
ref/core.py
refvar-0.3.3.dist-info/licenses/LICENSE
refvar-0.3.3.dist-info/METADATA
refvar-0.3.3.dist-info/WHEEL
refvar-0.3.3.dist-info/top_level.txt
refvar-0.3.3.dist-info/RECORD
