Metadata-Version: 2.4
Name: refvar
Version: 0.3.3
Summary: A lightweight reactive variable for simple values in Python.
Author-email: Emerson Erlando <emerson.mtr3@gmail.com>
License: MIT License
Project-URL: Homepage, https://github.com/Emersonmtr3-prog/refvar
Project-URL: Repository, https://github.com/Emersonmtr3-prog/refvar
Keywords: reactive,state,variable,ref,lightweight
Classifier: Programming Language :: Python :: 3
Classifier: Programming Language :: Python :: 3 :: Only
Classifier: License :: OSI Approved :: MIT License
Classifier: Intended Audience :: Developers
Classifier: Operating System :: OS Independent
Requires-Python: >=3.7
License-File: LICENSE
Dynamic: license-file
